esy/osm/topology/__init__.py
esy/osm/topology/cache.py
esy/osm/topology/graph.py
esy/osm/topology/mpl.py
esy/osm/topology/osm.py
esy/osm/topology/power.py
esy/osm/topology/test.py
esy_osm_topology-0.1.dist-info/LICENSE
esy_osm_topology-0.1.dist-info/METADATA
esy_osm_topology-0.1.dist-info/WHEEL
esy_osm_topology-0.1.dist-info/top_level.txt
esy_osm_topology-0.1.dist-info/RECORD
