Metadata-Version: 2.1
Name: esy-osm-topology
Version: 0.1
Summary: Construct topologies from visual data, like OpenStreetMap
Author-email: Ontje Lünsdorf <ontje.luensdorf@dlr.de>
License: BSD-3-Clause
Project-URL: homepage, https://gitlab.com/dlr-ve/esy/esy.osm.topology
Project-URL: documentation, https://dlr-ve.gitlab.io/esy/esy.osm.topology/
Project-URL: tracker, https://gitlab.com/dlr-ve/esy/esy.osm.topology/issues
Keywords: OSM,OpenStreetMap,shapely,topology,graph
Classifier: Development Status :: 5 - Production/Stable
Classifier: Environment :: Console
Classifier: Intended Audience :: Developers
Classifier: Intended Audience :: Education
Classifier: Intended Audience :: Science/Research
Classifier: License :: OSI Approved :: BSD License
Classifier: Natural Language :: English
Classifier: Operating System :: OS Independent
Classifier: Programming Language :: Python
Classifier: Programming Language :: Python :: 3
Classifier: Topic :: Scientific/Engineering
Requires-Python: >=3.9
License-File: LICENSE
Requires-Dist: numpy>=1.23
Requires-Dist: scipy>=1.10
Requires-Dist: shapely>=2
Requires-Dist: pyproj>=3.6.1
Requires-Dist: esy-osm-shape>=0.2
Provides-Extra: dev
Requires-Dist: pdoc; extra == "dev"
Requires-Dist: matplotlib; extra == "dev"
